MANIFEST.in
README.rst
requirements.txt
setup.cfg
setup.py
mochi/__init__.py
mochi.egg-info/PKG-INFO
mochi.egg-info/SOURCES.txt
mochi.egg-info/dependency_links.txt
mochi.egg-info/entry_points.txt
mochi.egg-info/requires.txt
mochi.egg-info/top_level.txt
mochi/actor/__init__.py
mochi/actor/actor.py
mochi/actor/mailbox.py
mochi/actor/message.py
mochi/core/__init__.py
mochi/core/builtins.py
mochi/core/constants.py
mochi/core/exceptions.py
mochi/core/global_env.py
mochi/core/import_global_env.mochi
mochi/core/import_global_env_and_monkey_patch.mochi
mochi/core/main.py
mochi/core/translation.py
mochi/core/utils.py
mochi/parser/__init__.py
mochi/parser/lexer.py
mochi/parser/parser.py
mochi/sexpressions/__init__.py
mochi/sexpressions/cpython.expr
mochi/sexpressions/del_hidden.expr
mochi/sexpressions/main.expr
mochi/sexpressions/pypy.expr
mochi/utils/__init__.py
mochi/utils/importer.py
mochi/utils/path_helper.py
mochi/utils/pycloader.py